Metadata-Version: 2.2
Name: libreflow.extensions.anpo.dependency_manager
Version: 1.1.0
Home-page: https://gitlab.com/lfs.coop/libreflow/extensions/anpo/dependency_manager
Author: LFS
Author-email: libreflow@lfs.coop
License: LGPLv3+
Keywords: kabaret libreflow
Classifier: Programming Language :: Python :: 3
Classifier: Intended Audience :: Developers
Classifier: License :: OSI Approved :: GNU Lesser General Public License v3 or later (LGPLv3+)
Classifier: Operating System :: OS Independent
Requires-Python: >=3.7
Requires-Dist: blender-asset-tracer
Requires-Dist: zstandard
Dynamic: author
Dynamic: author-email
Dynamic: classifier
Dynamic: description
Dynamic: description-content-type
Dynamic: home-page
Dynamic: keywords
Dynamic: license
Dynamic: requires-dist
Dynamic: requires-python
